gpio_button/__init__.py
gpio_button/button.py
gpio_button-0.1.dist-info/METADATA
gpio_button-0.1.dist-info/WHEEL
gpio_button-0.1.dist-info/top_level.txt
gpio_button-0.1.dist-info/RECORD
